README
setup.py
gmail/__init__.py
gmail/cli.py
gmail/gmail.py
gmail/message.py
gmail/test_gmail.py
gmail/test_message.py
gmail.egg-info/PKG-INFO
gmail.egg-info/SOURCES.txt
gmail.egg-info/dependency_links.txt
gmail.egg-info/top_level.txt