Metadata-Version: 1.0
Name: gmail
Version: 0.4
Summary: Simple library to send email using GMail (includes background worker and logging classes)
Home-page: https://github.com/paulchakravarti/gmail-sender
Author: Paul Chakravarti
Author-email: paul.chakravarti@gmail.com
License: BSD
Platform: UNKNOWN
Classifier: Topic :: Communications :: Email
